LICENSE
MANIFEST.in
README.md
setup.py
csf/__init__.py
csf/api.py
csf/conf.py
csf/util.py
csf.egg-info/PKG-INFO
csf.egg-info/SOURCES.txt
csf.egg-info/dependency_links.txt
csf.egg-info/top_level.txt